    {
        "activities": [
            {
                "size": 7,
                "items": [
                    {
                        "type": "move",
                        "date": 20170315,
                        "details": {
                            "sunrise": 1489558980,
                            "wo_active_time": 0,
                            "wo_time": 0,
                            "steps": 0,
                            "wo_calories": 0,
                            "km": 0,
                            "sunset": 1489601400,
                            "bg_calories": 0,
                            "bmr": 1232.20914223,
                            "wo_longest": 0,
                            "wo_count": 0,
                            "calories": 0,
                            "bmr_day": 1760.53880027,
                            "longest_idle": 0,
                            "longest_active": 0,
                            "tz": "Europe/London",
                            "tzs": [
                                [
                                    1489536052,
                                    "Europe/London"
                                ]
                            ],
                            "active_time": 0
                        },
                        "time_completed": 1489567277,
                        "time_created": 1489536052,
                        "snapshot_image": "",
                        "title": "0 steps today",
                        "xid": "hn0OLAb8ku__Y5SpSsAVdBlFsuP0mlzE",
                        "time_updated": 1489596471
                    },
                    {
                        "snapshot_image": "/nudge/image/e/1489567274/hn0OLAb8ku-vBVE273BQoIJwCTYeRCG7/eITeu_Bla0s.png",
                        "date": 20170314,
                        "details": {
                            "sunset": 1489514880,
                            "inactive_time": 32400,
                            "wo_calories": 0,
                            "steps": 29,
                            "km": 0.022,
                            "calories": 2.84685659409,
                            "longest_idle": 32400,
                            "longest_active": 0,
                            "tz": "Europe/London",
                            "distance": 22,
                            "sunrise": 1489472700,
                            "wo_active_time": 0,
                            "wo_time": 0,
                            "hourly_totals": {
                                "2017031420": {
                                    "longest_active_time": 0,
                                    "steps": 29,
                                    "longest_idle_time": 0,
                                    "inactive_time": 0,
                                    "calories": 2.84685659409,
                                    "active_time": 0,
                                    "distance": 22
                                }
                            },
                            "bg_calories": 2.84685659409,
                            "bmr": 1760.55730712,
                            "wo_longest": 0,
                            "wo_count": 0,
                            "bmr_day": 1760.55730712,
                            "steps_3am": 0,
                            "tzs": [
                                [
                                    1489513056,
                                    "Europe/London"
                                ]
                            ],
                            "active_time": 0
                        },
                        "time_completed": 1489523032,
                        "time_created": 1489522674,
                        "type": "move",
                        "title": "29 steps",
                        "xid": "hn0OLAb8ku-vBVE273BQoIJwCTYeRCG7",
                        "time_updated": 1489596471
                    },
                    {
                        "snapshot_image": "/nudge/image/e/1481291370/OLC3aS6nr3V15Ai5jf5Zk_nKJWYp_Ymp/eITeu_Bla0s.png",
                        "date": 20161209,
                        "details": {
                            "sunset": 1481297940,
                            "inactive_time": 18558,
                            "wo_calories": 0,
                            "steps": 1507,
                            "km": 1.218,
                            "calories": 121.480508732,
                            "longest_idle": 13603,
                            "longest_active": 361,
                            "tz": "Europe/London",
                            "distance": 1218,
                            "sunrise": 1481271540,
                            "wo_active_time": 0,
                            "wo_time": 0,
                            "hourly_totals": {
                                "2016120911": {
                                    "longest_active_time": 60,
                                    "steps": 130,
                                    "longest_idle_time": 2803,
                                    "inactive_time": 2924,
                                    "calories": 9.45735359192,
                                    "active_time": 120,
                                    "distance": 113
                                },
                                "2016120912": {
                                    "longest_active_time": 239,
                                    "steps": 540,
                                    "longest_idle_time": 2232,
                                    "inactive_time": 2946,
                                    "calories": 39.6991728544,
                                    "active_time": 478,
                                    "distance": 448
                                },
                                "2016120913": {
                                    "longest_active_time": 179,
                                    "steps": 837,
                                    "longest_idle_time": 786,
                                    "inactive_time": 1332,
                                    "calories": 49.1324003935,
                                    "active_time": 539,
                                    "distance": 657
                                }
                            },
                            "bg_calories": 98.2889268398,
                            "bmr": 1739.12387592,
                            "wo_longest": 0,
                            "wo_count": 0,
                            "bmr_day": 1739.12387592,
                            "steps_3am": 0,
                            "tzs": [
                                [
                                    1481241619,
                                    "Europe/London"
                                ]
                            ],
                            "active_time": 1137
                        },
                        "time_completed": 1481290522,
                        "time_created": 1481283396,
                        "type": "move",
                        "title": "1,507 steps",
                        "xid": "OLC3aS6nr3V15Ai5jf5Zk_nKJWYp_Ymp",
                        "time_updated": 1489596471
                    },
                    {
                        "type": "move",
                        "date": 20161208,
                        "details": {
                            "inactive_time": 14523,
                            "wo_time": 0,
                            "wo_calories": 0,
                            "sunset": 1481211540,
                            "km": 2.42,
                            "calories": 232.823589211,
                            "longest_idle": 3326,
                            "longest_active": 482,
                            "tz": "Europe/London",
                            "distance": 2420,
                            "sunrise": 1481271540,
                            "wo_active_time": 0,
                            "bmr_day": 1712.09520823,
                            "hourly_totals": {
                                "2016120808": {
                                    "longest_active_time": 182,
                                    "steps": 171,
                                    "longest_idle_time": 2820,
                                    "inactive_time": 3005,
                                    "calories": 13.1365543604,
                                    "active_time": 243,
                                    "distance": 134
                                },
                                "2016120809": {
                                    "longest_active_time": 362,
                                    "steps": 803,
                                    "longest_idle_time": 1030,
                                    "inactive_time": 1336,
                                    "calories": 44.1504024267,
                                    "active_time": 540,
                                    "distance": 631
                                },
                                "2016120810": {
                                    "longest_active_time": 482,
                                    "steps": 1425,
                                    "longest_idle_time": 1870,
                                    "inactive_time": 2191,
                                    "calories": 75.9000897408,
                                    "active_time": 1077,
                                    "distance": 1110
                                },
                                "2016120811": {
                                    "longest_active_time": 178,
                                    "steps": 183,
                                    "longest_idle_time": 3241,
                                    "inactive_time": 3300,
                                    "calories": 15.2475705147,
                                    "active_time": 178,
                                    "distance": 146
                                },
                                "2016120812": {
                                    "longest_active_time": 123,
                                    "steps": 524,
                                    "longest_idle_time": 1506,
                                    "inactive_time": 2412,
                                    "calories": 34.150215745,
                                    "active_time": 425,
                                    "distance": 399
                                }
                            },
                            "bg_calories": 182.584832788,
                            "steps": 3106,
                            "bmr": 1712.09520823,
                            "wo_longest": 0,
                            "wo_count": 0,
                            "steps_3am": 0,
                            "tzs": [
                                [
                                    1481155222,
                                    "Europe/London"
                                ]
                            ],
                            "active_time": 2463
                        },
                        "time_completed": 1481201413,
                        "time_created": 1481186700,
                        "snapshot_image": "/nudge/image/e/1481291194/OLC3aS6nr3VDx-Le3ObvqF_GphNchWwX/eITeu_Bla0s.png",
                        "title": "3,106 steps",
                        "xid": "OLC3aS6nr3VDx-Le3ObvqF_GphNchWwX",
                        "time_updated": 1489596471
                    },
                    {
                        "type": "move",
                        "date": 20161207,
                        "details": {
                            "inactive_time": 29090,
                            "wo_time": 0,
                            "wo_calories": 0,
                            "sunset": 1481125140,
                            "km": 6.295,
                            "calories": 586.51766555,
                            "longest_idle": 10957,
                            "longest_active": 897,
                            "tz": "Europe/London",
                            "distance": 6295,
                            "sunrise": 1481185080,
                            "wo_active_time": 0,
                            "bmr_day": 1645.43343949,
                            "hourly_totals": {
                                "2016120710": {
                                    "longest_active_time": 299,
                                    "steps": 601,
                                    "longest_idle_time": 2228,
                                    "inactive_time": 2944,
                                    "calories": 39.4820389748,
                                    "active_time": 358,
                                    "distance": 486
                                },
                                "2016120711": {
                                    "longest_active_time": 897,
                                    "steps": 1638,
                                    "longest_idle_time": 1441,
                                    "inactive_time": 1500,
                                    "calories": 96.6242421865,
                                    "active_time": 897,
                                    "distance": 1409
                                },
                                "2016120712": {
                                    "longest_active_time": 119,
                                    "steps": 76,
                                    "longest_idle_time": 3324,
                                    "inactive_time": 3324,
                                    "calories": 5.75402760506,
                                    "active_time": 119,
                                    "distance": 58
                                },
                                "2016120713": {
                                    "longest_active_time": 717,
                                    "steps": 2144,
                                    "longest_idle_time": 786,
                                    "inactive_time": 1625,
                                    "calories": 116.914124012,
                                    "active_time": 1319,
                                    "distance": 1689
                                },
                                "2016120714": {
                                    "longest_active_time": 0,
                                    "steps": 30,
                                    "longest_idle_time": 1787,
                                    "inactive_time": 1787,
                                    "calories": 4.39091432095,
                                    "active_time": 0,
                                    "distance": 20
                                },
                                "2016120715": {
                                    "longest_active_time": 0,
                                    "steps": 15,
                                    "longest_idle_time": 2758,
                                    "inactive_time": 2758,
                                    "calories": 2.91923415661,
                                    "active_time": 0,
                                    "distance": 10
                                },
                                "2016120716": {
                                    "longest_active_time": 241,
                                    "steps": 372,
                                    "longest_idle_time": 2466,
                                    "inactive_time": 2890,
                                    "calories": 23.2814962864,
                                    "active_time": 302,
                                    "distance": 285
                                },
                                "2016120717": {
                                    "longest_active_time": 237,
                                    "steps": 592,
                                    "longest_idle_time": 0,
                                    "inactive_time": 0,
                                    "calories": 29.988497138,
                                    "active_time": 531,
                                    "distance": 433
                                },
                                "2016120718": {
                                    "longest_active_time": 59,
                                    "steps": 49,
                                    "longest_idle_time": 0,
                                    "inactive_time": 0,
                                    "calories": 2.84685659409,
                                    "active_time": 59,
                                    "distance": 39
                                },
                                "2016120719": {
                                    "longest_active_time": 0,
                                    "steps": 52,
                                    "longest_idle_time": 0,
                                    "inactive_time": 0,
                                    "calories": 5.74196493626,
                                    "active_time": 0,
                                    "distance": 46
                                },
                                "2016120720": {
                                    "longest_active_time": 120,
                                    "steps": 133,
                                    "longest_idle_time": 0,
                                    "inactive_time": 0,
                                    "calories": 9.39703941345,
                                    "active_time": 120,
                                    "distance": 118
                                },
                                "2016120721": {
                                    "longest_active_time": 298,
                                    "steps": 1066,
                                    "longest_idle_time": 0,
                                    "inactive_time": 0,
                                    "calories": 78.1437983513,
                                    "active_time": 1250,
                                    "distance": 1008
                                },
                                "2016120722": {
                                    "longest_active_time": 299,
                                    "steps": 652,
                                    "longest_idle_time": 0,
                                    "inactive_time": 0,
                                    "calories": 41.8343153,
                                    "active_time": 658,
                                    "distance": 567
                                },
                                "2016120723": {
                                    "longest_active_time": 61,
                                    "steps": 172,
                                    "longest_idle_time": 0,
                                    "inactive_time": 0,
                                    "calories": 12.2800842524,
                                    "active_time": 119,
                                    "distance": 127
                                }
                            },
                            "bg_calories": 469.598633528,
                            "steps": 7592,
                            "bmr": 1645.43343949,
                            "wo_longest": 0,
                            "wo_count": 0,
                            "steps_3am": 0,
                            "tzs": [
                                [
                                    1481068841,
                                    "Europe/London"
                                ]
                            ],
                            "active_time": 5732
                        },
                        "time_completed": 1481153600,
                        "time_created": 1481107028,
                        "snapshot_image": "/nudge/image/e/1481291189/OLC3aS6nr3Uz5An8iGlNeAMeasuwmFWa/eITeu_Bla0s.png",
                        "title": "7,592 steps",
                        "xid": "OLC3aS6nr3Uz5An8iGlNeAMeasuwmFWa",
                        "time_updated": 1489596471
                    },
                    {
                        "type": "move",
                        "date": 20161206,
                        "details": {
                            "inactive_time": 29423,
                            "wo_time": 0,
                            "wo_calories": 0,
                            "sunset": 1481038800,
                            "km": 6.755,
                            "calories": 655.442150795,
                            "longest_idle": 9597,
                            "longest_active": 659,
                            "tz": "Europe/London",
                            "distance": 6755,
                            "sunrise": 1481098620,
                            "wo_active_time": 0,
                            "bmr_day": 1628.3981475,
                            "hourly_totals": {
                                "2016120603": {
                                    "longest_active_time": 600,
                                    "steps": 1399,
                                    "longest_idle_time": 0,
                                    "inactive_time": 0,
                                    "calories": 103.391554952,
                                    "active_time": 1019,
                                    "distance": 1319
                                },
                                "2016120604": {
                                    "longest_active_time": 659,
                                    "steps": 1208,
                                    "longest_idle_time": 0,
                                    "inactive_time": 0,
                                    "calories": 82.0521947145,
                                    "active_time": 1133,
                                    "distance": 1127
                                },
                                "2016120607": {
                                    "longest_active_time": 180,
                                    "steps": 731,
                                    "longest_idle_time": 0,
                                    "inactive_time": 0,
                                    "calories": 46.2493556738,
                                    "active_time": 657,
                                    "distance": 576
                                },
                                "2016120608": {
                                    "longest_active_time": 59,
                                    "steps": 33,
                                    "longest_idle_time": 0,
                                    "inactive_time": 0,
                                    "calories": 2.13514232635,
                                    "active_time": 59,
                                    "distance": 26
                                },
                                "2016120609": {
                                    "longest_active_time": 182,
                                    "steps": 673,
                                    "longest_idle_time": 1624,
                                    "inactive_time": 3056,
                                    "calories": 44.8862410784,
                                    "active_time": 540,
                                    "distance": 536
                                },
                                "2016120610": {
                                    "longest_active_time": 59,
                                    "steps": 35,
                                    "longest_idle_time": 0,
                                    "inactive_time": 0,
                                    "calories": 2.13514232635,
                                    "active_time": 59,
                                    "distance": 25
                                },
                                "2016120611": {
                                    "longest_active_time": 239,
                                    "steps": 515,
                                    "longest_idle_time": 1797,
                                    "inactive_time": 1918,
                                    "calories": 33.5953199863,
                                    "active_time": 298,
                                    "distance": 453
                                },
                                "2016120612": {
                                    "longest_active_time": 657,
                                    "steps": 1834,
                                    "longest_idle_time": 187,
                                    "inactive_time": 548,
                                    "calories": 95.2369993925,
                                    "active_time": 1254,
                                    "distance": 1411
                                },
                                "2016120613": {
                                    "longest_active_time": 58,
                                    "steps": 52,
                                    "longest_idle_time": 1230,
                                    "inactive_time": 1288,
                                    "calories": 3.59475946426,
                                    "active_time": 58,
                                    "distance": 42
                                },
                                "2016120616": {
                                    "longest_active_time": 178,
                                    "steps": 692,
                                    "longest_idle_time": 1389,
                                    "inactive_time": 2320,
                                    "calories": 43.788513422,
                                    "active_time": 594,
                                    "distance": 556
                                },
                                "2016120617": {
                                    "longest_active_time": 118,
                                    "steps": 456,
                                    "longest_idle_time": 0,
                                    "inactive_time": 0,
                                    "calories": 34.7051104307,
                                    "active_time": 416,
                                    "distance": 352
                                },
                                "2016120618": {
                                    "longest_active_time": 183,
                                    "steps": 210,
                                    "longest_idle_time": 0,
                                    "inactive_time": 0,
                                    "calories": 15.3440740108,
                                    "active_time": 243,
                                    "distance": 166
                                },
                                "2016120619": {
                                    "longest_active_time": 178,
                                    "steps": 188,
                                    "longest_idle_time": 0,
                                    "inactive_time": 0,
                                    "calories": 14.3549121618,
                                    "active_time": 238,
                                    "distance": 166
                                }
                            },
                            "bg_calories": 521.46931994,
                            "steps": 8026,
                            "bmr": 1628.3981475,
                            "wo_longest": 0,
                            "wo_count": 0,
                            "steps_3am": 0,
                            "tzs": [
                                [
                                    1480982427,
                                    "Europe/London"
                                ]
                            ],
                            "active_time": 6568
                        },
                        "time_completed": 1481053414,
                        "time_created": 1480993289,
                        "snapshot_image": "/nudge/image/e/1481291185/OLC3aS6nr3WbieKK9JgEPV9O87DKVAIp/eITeu_Bla0s.png",
                        "title": "8,026 steps",
                        "xid": "OLC3aS6nr3WbieKK9JgEPV9O87DKVAIp",
                        "time_updated": 1489596471
                    },
                    {
                        "snapshot_image": "/nudge/image/e/1481291180/OLC3aS6nr3V5coHPP04B6frCnrWCpnxN/eITeu_Bla0s.png",
                        "date": 20161205,
                        "details": {
                            "inactive_time": 6215,
                            "sunset": 1480952400,
                            "wo_time": 0,
                            "wo_calories": 0,
                            "steps": 4637,
                            "km": 3.782,
                            "calories": 377.173364586,
                            "longest_idle": 4585,
                            "longest_active": 779,
                            "tz": "Europe/London",
                            "distance": 3782,
                            "sunrise": 1480925640,
                            "wo_active_time": 0,
                            "bmr_day": 1690.1192775,
                            "hourly_totals": {
                                "2016120515": {
                                    "longest_active_time": 181,
                                    "steps": 370,
                                    "longest_idle_time": 1415,
                                    "inactive_time": 2796,
                                    "calories": 20.3743243217,
                                    "active_time": 181,
                                    "distance": 272
                                },
                                "2016120516": {
                                    "longest_active_time": 239,
                                    "steps": 510,
                                    "longest_idle_time": 2968,
                                    "inactive_time": 3149,
                                    "calories": 38.1671779156,
                                    "active_time": 239,
                                    "distance": 422
                                },
                                "2016120517": {
                                    "longest_active_time": 122,
                                    "steps": 389,
                                    "longest_idle_time": 0,
                                    "inactive_time": 0,
                                    "calories": 23.9328953028,
                                    "active_time": 302,
                                    "distance": 278
                                },
                                "2016120518": {
                                    "longest_active_time": 122,
                                    "steps": 492,
                                    "longest_idle_time": 0,
                                    "inactive_time": 0,
                                    "calories": 28.3479362726,
                                    "active_time": 422,
                                    "distance": 348
                                },
                                "2016120519": {
                                    "longest_active_time": 423,
                                    "steps": 1121,
                                    "longest_idle_time": 0,
                                    "inactive_time": 0,
                                    "calories": 62.4016468525,
                                    "active_time": 781,
                                    "distance": 815
                                },
                                "2016120520": {
                                    "longest_active_time": 779,
                                    "steps": 851,
                                    "longest_idle_time": 0,
                                    "inactive_time": 0,
                                    "calories": 61.6054934263,
                                    "active_time": 900,
                                    "distance": 825
                                },
                                "2016120521": {
                                    "longest_active_time": 61,
                                    "steps": 102,
                                    "longest_idle_time": 0,
                                    "inactive_time": 0,
                                    "calories": 8.78182852268,
                                    "active_time": 61,
                                    "distance": 72
                                },
                                "2016120522": {
                                    "longest_active_time": 179,
                                    "steps": 631,
                                    "longest_idle_time": 0,
                                    "inactive_time": 0,
                                    "calories": 49.6511063576,
                                    "active_time": 476,
                                    "distance": 621
                                },
                                "2016120523": {
                                    "longest_active_time": 120,
                                    "steps": 171,
                                    "longest_idle_time": 0,
                                    "inactive_time": 0,
                                    "calories": 11.6407479048,
                                    "active_time": 181,
                                    "distance": 129
                                }
                            },
                            "bg_calories": 304.903156877,
                            "bmr": 1690.1192775,
                            "wo_longest": 0,
                            "wo_count": 0,
                            "steps_3am": 0,
                            "tzs": [
                                [
                                    1480951558,
                                    "Europe/London"
                                ]
                            ],
                            "active_time": 3543
                        },
                        "time_completed": 1480979172,
                        "time_created": 1480951558,
                        "type": "move",
                        "title": "4,637 steps",
                        "xid": "OLC3aS6nr3V5coHPP04B6frCnrWCpnxN",
                        "time_updated": 1489596471
                    }
                ]
            },
            {
                "size": 0,
                "items": []
            },
            {
                "size": 2,
                "items": [
                    {
                        "place_name": "",
                        "place_acc": "",
                        "sub_type": 0,
                        "snapshot_image": "/nudge/image/e/1489590538/hn0OLAb8ku9uv0GKjRNb1sk8peGK7V6w/eITeu_Bla0s.png",
                        "shared": true,
                        "date": 20170314,
                        "place_lat": "",
                        "details": {
                            "sunset": 1489514820,
                            "sunrise": 1489558980,
                            "awake_time": 1489530549,
                            "quality": 0,
                            "smart_alarm_fire": 0,
                            "duration": 1825,
                            "rem": 0,
                            "awake": 360,
                            "asleep_time": 1489529084,
                            "mind": 0,
                            "light": 0,
                            "awakenings": 0,
                            "tz": "Europe/London",
                            "sound": 1465,
                            "body": 0
                        },
                        "time_updated": 1489590538,
                        "time_created": 1489528784,
                        "title": "for 24m",
                        "xid": "hn0OLAb8ku9uv0GKjRNb1sk8peGK7V6w",
                        "time_completed": 1489530609,
                        "place_lon": ""
                    },
                    {
                        "place_name": "",
                        "place_acc": "",
                        "sub_type": 0,
                        "snapshot_image": "/nudge/image/e/1481291185/OLC3aS6nr3WgzH7BaZV6dDRObUPDluNq/eITeu_Bla0s.png",
                        "shared": true,
                        "date": 20161206,
                        "place_lat": "",
                        "details": {
                            "sunrise": null,
                            "sunset": null,
                            "quality": "",
                            "smart_alarm_fire": "",
                            "duration": 11735,
                            "rem": 2600,
                            "awake": 600,
                            "awake_time": 1480993199,
                            "asleep_time": 1480982064,
                            "mind": 0,
                            "light": 6308,
                            "awakenings": 0,
                            "tz": "Europe/London",
                            "sound": 2227,
                            "body": ""
                        },
                        "time_updated": 1481291185,
                        "time_created": 1480981464,
                        "title": "for 3h 5m",
                        "xid": "OLC3aS6nr3WgzH7BaZV6dDRObUPDluNq",
                        "time_completed": 1480993199,
                        "place_lon": ""
                    }
                ]
            },
            {
                "size": 0,
                "items": []
            },
            null
        ],
        "profile": [
            {
                "first": "Craig",
                "last": "Sharp",
                "height": 1.778,
                "image": "user/image/i/82fb841408de11e7b13222000b508eeb_RGaCBFg9CsCVeDYBM5FYsg_148951374313_1068778_photo.png",
                "gender": false,
                "weight": 78,
                "xid": "-9VI7q6PJcpT0RF0ruzMEA"
            },
            null,
            null,
            {
                "links": {
                    "next": "/nudge/api/v.1.1/users/-9VI7q6PJcpT0RF0ruzMEA/trends/?end_date=20170308&bucket_size=d&num_buckets=7"
                },
                "data": [
                    [
                        20170309,
                        {
                            "n_asleep_time": null,
                            "n_awake": null,
                            "n_awake_time": null,
                            "n_quality": null,
                            "s_sound": null,
                            "e_fiber": null,
                            "e_carbs": null,
                            "age": 39.6520547945,
                            "gender": 0,
                            "s_duration": null,
                            "e_sugar": null,
                            "s_awake": null,
                            "e_sodium": null,
                            "s_asleep_time": null,
                            "n_sound": null,
                            "m_total_calories": 1760.64984137,
                            "bmr": 1760.64984137,
                            "e_calories": null,
                            "m_calories": null,
                            "e_unsat_fat": null,
                            "m_active_time": null,
                            "m_lcit": null,
                            "n_duration": null,
                            "pal": null,
                            "s_awake_time": null,
                            "n_light": null,
                            "n_awakenings": null,
                            "s_bedtime": null,
                            "e_calcium": null,
                            "m_workout_time": null,
                            "n_bedtime": null,
                            "e_sat_fat": null,
                            "s_light": null,
                            "e_cholesterol": null,
                            "m_steps": null,
                            "s_quality": null,
                            "goal_body_weight": null,
                            "m_lcat": null,
                            "height": 1.778,
                            "s_awakenings": null,
                            "m_distance": null,
                            "body_fat": 0,
                            "goal_body_weight_intent": 0,
                            "weight": 78,
                            "e_protein": null
                        }
                    ],
                    [
                        20170310,
                        {
                            "n_asleep_time": null,
                            "gender": 0,
                            "n_awake_time": null,
                            "n_quality": null,
                            "m_steps": null,
                            "e_fiber": null,
                            "e_carbs": null,
                            "age": 39.6547945205,
                            "n_awake": null,
                            "s_duration": null,
                            "s_asleep_time": null,
                            "s_awake": null,
                            "e_sodium": null,
                            "e_sugar": null,
                            "n_sound": null,
                            "m_total_calories": 1760.63133452,
                            "bmr": 1760.63133452,
                            "m_calories": null,
                            "e_unsat_fat": null,
                            "m_active_time": null,
                            "m_lcit": null,
                            "n_duration": null,
                            "pal": null,
                            "s_sound": null,
                            "s_awake_time": null,
                            "n_light": null,
                            "n_awakenings": null,
                            "s_bedtime": null,
                            "e_calcium": null,
                            "m_workout_time": null,
                            "n_bedtime": null,
                            "e_sat_fat": null,
                            "s_light": null,
                            "e_cholesterol": null,
                            "e_calories": null,
                            "s_quality": null,
                            "goal_body_weight": null,
                            "m_lcat": null,
                            "height": 1.778,
                            "s_awakenings": null,
                            "m_distance": null,
                            "body_fat": 0,
                            "goal_body_weight_intent": 0,
                            "weight": 78,
                            "e_protein": null
                        }
                    ],
                    [
                        20170311,
                        {
                            "n_asleep_time": null,
                            "gender": 0,
                            "n_awake_time": null,
                            "m_lcit": null,
                            "s_sound": null,
                            "e_fiber": null,
                            "e_carbs": null,
                            "age": 39.6575342466,
                            "n_awake": null,
                            "n_quality": null,
                            "s_duration": null,
                            "e_sugar": null,
                            "s_awake": null,
                            "e_sodium": null,
                            "s_asleep_time": null,
                            "n_sound": null,
                            "m_total_calories": 1760.61282767,
                            "bmr": 1760.61282767,
                            "m_calories": null,
                            "e_unsat_fat": null,
                            "m_active_time": null,
                            "m_steps": null,
                            "n_duration": null,
                            "pal": null,
                            "s_awake_time": null,
                            "n_light": null,
                            "n_awakenings": null,
                            "s_bedtime": null,
                            "e_calcium": null,
                            "m_workout_time": null,
                            "n_bedtime": null,
                            "e_sat_fat": null,
                            "s_light": null,
                            "e_cholesterol": null,
                            "e_calories": null,
                            "s_quality": null,
                            "goal_body_weight": null,
                            "m_lcat": null,
                            "height": 1.778,
                            "s_awakenings": null,
                            "m_distance": null,
                            "body_fat": 0,
                            "goal_body_weight_intent": 0,
                            "weight": 78,
                            "e_protein": null
                        }
                    ],
                    [
                        20170312,
                        {
                            "n_asleep_time": null,
                            "n_awake": null,
                            "n_awake_time": null,
                            "n_quality": null,
                            "m_steps": null,
                            "e_fiber": null,
                            "e_carbs": null,
                            "age": 39.6602739726,
                            "gender": 0,
                            "s_duration": null,
                            "e_sugar": null,
                            "s_awake": null,
                            "e_sodium": null,
                            "s_asleep_time": null,
                            "n_sound": null,
                            "m_total_calories": 1760.59432082,
                            "bmr": 1760.59432082,
                            "m_calories": null,
                            "e_unsat_fat": null,
                            "m_active_time": null,
                            "m_lcit": null,
                            "n_duration": null,
                            "pal": null,
                            "s_sound": null,
                            "s_awake_time": null,
                            "n_light": null,
                            "n_awakenings": null,
                            "s_bedtime": null,
                            "e_calcium": null,
                            "m_workout_time": null,
                            "n_bedtime": null,
                            "e_sat_fat": null,
                            "s_light": null,
                            "e_cholesterol": null,
                            "e_calories": null,
                            "s_quality": null,
                            "goal_body_weight": null,
                            "m_lcat": null,
                            "height": 1.778,
                            "s_awakenings": null,
                            "m_distance": null,
                            "body_fat": 0,
                            "goal_body_weight_intent": 0,
                            "weight": 78,
                            "e_protein": null
                        }
                    ],
                    [
                        20170313,
                        {
                            "n_asleep_time": null,
                            "gender": 0,
                            "n_awake_time": null,
                            "m_lcit": null,
                            "s_sound": null,
                            "e_fiber": null,
                            "e_carbs": null,
                            "age": 39.6630136986,
                            "n_awake": null,
                            "n_quality": null,
                            "s_duration": null,
                            "s_asleep_time": null,
                            "s_awake": null,
                            "e_sodium": null,
                            "e_sugar": null,
                            "n_sound": null,
                            "m_total_calories": 1760.57581397,
                            "bmr": 1760.57581397,
                            "m_calories": null,
                            "e_unsat_fat": null,
                            "m_active_time": null,
                            "e_calories": null,
                            "n_duration": null,
                            "pal": null,
                            "s_awake_time": null,
                            "n_light": null,
                            "n_awakenings": null,
                            "s_bedtime": null,
                            "e_calcium": null,
                            "m_workout_time": null,
                            "n_bedtime": null,
                            "e_sat_fat": null,
                            "s_light": null,
                            "e_cholesterol": null,
                            "m_steps": null,
                            "s_quality": null,
                            "goal_body_weight": null,
                            "m_lcat": null,
                            "height": 1.778,
                            "s_awakenings": null,
                            "m_distance": null,
                            "body_fat": 0,
                            "goal_body_weight_intent": 0,
                            "weight": 78,
                            "e_protein": null
                        }
                    ],
                    [
                        20170314,
                        {
                            "n_asleep_time": null,
                            "n_awake": null,
                            "n_awake_time": null,
                            "n_quality": null,
                            "s_sound": 0,
                            "e_fiber": null,
                            "e_carbs": null,
                            "age": 39.6657534247,
                            "s_awake_time": 80949,
                            "s_duration": 1465,
                            "s_asleep_time": 79484,
                            "s_awake": 360,
                            "e_sodium": null,
                            "e_sugar": null,
                            "n_sound": null,
                            "m_total_calories": 1763.40416372,
                            "bmr": 1760.55730712,
                            "m_calories": 2.84685659408,
                            "e_unsat_fat": null,
                            "m_active_time": 0,
                            "m_lcit": 32400,
                            "n_duration": null,
                            "pal": null,
                            "m_steps": 29,
                            "n_light": null,
                            "n_awakenings": null,
                            "s_bedtime": 79184,
                            "e_calcium": null,
                            "m_workout_time": 0,
                            "n_bedtime": null,
                            "e_sat_fat": null,
                            "s_light": 0,
                            "e_cholesterol": null,
                            "e_calories": null,
                            "s_quality": 0,
                            "goal_body_weight": null,
                            "gender": 0,
                            "m_lcat": 0,
                            "height": 1.778,
                            "s_awakenings": 0,
                            "m_distance": 22,
                            "body_fat": 0,
                            "goal_body_weight_intent": 0,
                            "weight": 78,
                            "e_protein": null
                        }
                    ],
                    [
                        20170315,
                        {
                            "n_asleep_time": null,
                            "gender": 0,
                            "n_awake_time": null,
                            "n_quality": null,
                            "s_sound": null,
                            "e_fiber": null,
                            "e_carbs": null,
                            "age": 39.6684931507,
                            "n_awake": null,
                            "s_duration": null,
                            "e_sugar": null,
                            "s_awake": null,
                            "e_sodium": null,
                            "s_asleep_time": null,
                            "n_sound": null,
                            "m_lcit": 0,
                            "m_total_calories": 718.682910714,
                            "bmr": 1760.53880027,
                            "m_calories": 0,
                            "e_unsat_fat": null,
                            "m_active_time": 0,
                            "e_calories": null,
                            "n_duration": null,
                            "pal": null,
                            "s_awake_time": null,
                            "n_light": null,
                            "n_awakenings": null,
                            "s_bedtime": null,
                            "e_calcium": null,
                            "m_workout_time": 0,
                            "n_bedtime": null,
                            "e_sat_fat": null,
                            "s_light": null,
                            "e_cholesterol": null,
                            "m_steps": 0,
                            "s_quality": null,
                            "goal_body_weight": null,
                            "m_lcat": 0,
                            "height": 1.778,
                            "s_awakenings": null,
                            "m_distance": 0,
                            "body_fat": 0,
                            "goal_body_weight_intent": 0,
                            "weight": 78,
                            "e_protein": null
                        }
                    ]
                ],
                "earliest": 20161205
            },
            {
                "eat_carbs": null,
                "body_weight_intent": 0,
                "move_steps": 10000,
                "eat_sugar": null,
                "remaining_for_day": {
                    "move_steps_remaining": 10000,
                    "intake_calories_remaining": 1260.53880027,
                    "sleep_seconds_remaining": 28800
                },
                "eat_calcium": null,
                "eat_protein": null,
                "eat_fiber": null,
                "sleep_total": 28800,
                "eat_cholesterol": null,
                "eat_unsat_fat": null,
                "body_weight": null,
                "eat_sodium": null,
                "eat_sat_fat": null
            }
        ]
    }